[
  {
    "id": 13657114,
    "title": "Viasat Kino Channel Rebrand",
    "web_url": "https://www.xinpianchang.com/a13657114",
    "cover": "https://us-xpc5.xpccdn.com/8afb72dd-72ec-4332-8a0e-4a4b43629d9f/e4d51f3e-5f43-4d65-ae56-455184b44555.jpg",
    "duration": 0,
    "categories": "宣传片-其他视觉探索-视觉艺术",
    "count_view": 2313,
    "count_like": 394,
    "count_collect": 0,
    "author": "栖光文化"
  },
  {
    "id": 13657100,
    "title": "Un Centre For Innovation",
    "web_url": "https://www.xinpianchang.com/a13657100",
    "cover": "https://us-xpc5.xpccdn.com/cdfe3803-b28d-4b8d-b0f1-555fe22aa4f4/944e31c3-9919-43fc-a8dd-f8199a085a73.jpg",
    "duration": 0,
    "categories": "三维CG-三维动画",
    "count_view": 167,
    "count_like": 168,
    "count_collect": 0,
    "author": "栖光文化"
  },
  {
    "id": 13657099,
    "title": "The System Is Updated - Behind The Scene",
    "web_url": "https://www.xinpianchang.com/a13657099",
    "cover": "https://us-xpc5.xpccdn.com/70ecbcaf-4fe2-4f54-9d41-53b047abf465/0ea65e1c-96dd-435b-8061-64f670cd8c8c.jpg",
    "duration": 0,
    "categories": "二维动画-数字动画",
    "count_view": 211,
    "count_like": 214,
    "count_collect": 0,
    "author": "栖光文化"
  },
  {
    "id": 13657098,
    "title": "The System Is Updated",
    "web_url": "https://www.xinpianchang.com/a13657098",
    "cover": "https://us-xpc5.xpccdn.com/ceaa3a2a-d068-4fbb-8311-076aa9780dc4/d96901cf-9318-4083-affe-d2aba201af12.jpg",
    "duration": 0,
    "categories": "视觉探索-视觉艺术",
    "count_view": 163,
    "count_like": 160,
    "count_collect": 0,
    "author": "栖光文化"
  },
  {
    "id": 13657097,
    "title": "Sulfur",
    "web_url": "https://www.xinpianchang.com/a13657097",
    "cover": "https://us-xpc5.xpccdn.com/c4f6ce5a-3d3a-4967-8bca-5c2c3932d5f4/239d2dc9-55d9-42da-bfcd-fc95b54f42b7.jpg",
    "duration": 0,
    "categories": "广告片-TVC广告",
    "count_view": 203,
    "count_like": 206,
    "count_collect": 0,
    "author": "栖光文化"
  },
  {
    "id": 13657096,
    "title": "Samsonite Campaign - Behind the Scenes",
    "web_url": "https://www.xinpianchang.com/a13657096",
    "cover": "https://us-xpc5.xpccdn.com/1af69776-791e-4e48-ad57-1b81c9e6f17a/49bb5376-f0ea-4497-ba27-22ff311b2877.jpg",
    "duration": 0,
    "categories": "广告片-产品广告三维CG-三维动画",
    "count_view": 187,
    "count_like": 182,
    "count_collect": 0,
    "author": "栖光文化"
  },
  {
    "id": 13657095,
    "title": "Samsonite Campaign",
    "web_url": "https://www.xinpianchang.com/a13657095",
    "cover": "https://us-xpc5.xpccdn.com/773e25fe-394c-42fb-844f-388dedabce42/67db5cd2-57ef-4bd2-9f06-c364a41f4a36.jpg",
    "duration": 0,
    "categories": "广告片-产品广告三维CG-三维动画",
    "count_view": 2178,
    "count_like": 359,
    "count_collect": 0,
    "author": "栖光文化"
  },
  {
    "id": 13657094,
    "title": "Reoplay H95 - Behind the Scenes",
    "web_url": "https://www.xinpianchang.com/a13657094",
    "cover": "https://us-xpc5.xpccdn.com/485f21de-0f50-493d-a165-d0dff72b4a57/f8df80c8-1a23-41c4-b0eb-a1a9a05e8d75.jpg",
    "duration": 0,
    "categories": "广告片-手机/数码",
    "count_view": 217,
    "count_like": 210,
    "count_collect": 0,
    "author": "栖光文化"
  },
  {
    "id": 13657093,
    "title": "Reoplay H95",
    "web_url": "https://www.xinpianchang.com/a13657093",
    "cover": "https://us-xpc5.xpccdn.com/d0cb44f5-c3da-47ec-b551-01baccb86855/e2e7140c-0511-45fa-9467-7218fbb3c5f1.jpg",
    "duration": 0,
    "categories": "广告片-产品广告三维CG-CG/特效",
    "count_view": 2343,
    "count_like": 400,
    "count_collect": 0,
    "author": "栖光文化"
  },
  {
    "id": 13657092,
    "title": "Powell Lacrosse",
    "web_url": "https://www.xinpianchang.com/a13657092",
    "cover": "https://us-xpc5.xpccdn.com/cbf2f328-7579-47d9-81b5-f781acd472df/3518c4de-2df7-4150-9fef-ae56199bdd9e.jpg",
    "duration": 0,
    "categories": "视觉探索-视觉艺术广告片-体育/运动",
    "count_view": 2259,
    "count_like": 389,
    "count_collect": 0,
    "author": "栖光文化"
  },
  {
    "id": 13657091,
    "title": "Nobjects - Behind the Scenes",
    "web_url": "https://www.xinpianchang.com/a13657091",
    "cover": "https://us-xpc5.xpccdn.com/2ac0cbdc-f8e6-4189-89b9-13cc72219aba/e2187397-42d7-4824-8c10-ea1ee391e329.jpg",
    "duration": 0,
    "categories": "三维CG-三维动画",
    "count_view": 214,
    "count_like": 213,
    "count_collect": 0,
    "author": "栖光文化"
  },
  {
    "id": 13657077,
    "title": "Nobjects",
    "web_url": "https://www.xinpianchang.com/a13657077",
    "cover": "https://us-xpc5.xpccdn.com/1e2314f6-971c-4666-b411-11ab18d2fc1f/86316374-2cc1-412d-ab82-0724281842ff.jpg",
    "duration": 0,
    "categories": "三维CG-三维动画广告片-家居",
    "count_view": 195,
    "count_like": 191,
    "count_collect": 0,
    "author": "栖光文化"
  },
  {
    "id": 13657011,
    "title": "Netflix Sirens Main Titles",
    "web_url": "https://www.xinpianchang.com/a13657011",
    "cover": "https://us-xpc5.xpccdn.com/3e931897-6690-4173-8c60-3881b0996d58/152f7471-da75-4218-ad31-9566f36aced1.jpg",
    "duration": 0,
    "categories": "三维CG-三维动画",
    "count_view": 188,
    "count_like": 186,
    "count_collect": 0,
    "author": "栖光文化"
  },
  {
    "id": 13657010,
    "title": "Murderbot",
    "web_url": "https://www.xinpianchang.com/a13657010",
    "cover": "https://us-xpc5.xpccdn.com/1d4fe4ca-ea1c-4149-80f2-4327538ed247/598febcb-bbbe-43e4-a778-ba11df3736b5.jpg",
    "duration": 0,
    "categories": "广告片-TVC广告",
    "count_view": 2174,
    "count_like": 355,
    "count_collect": 0,
    "author": "栖光文化"
  },
  {
    "id": 13657009,
    "title": "Moonkettle",
    "web_url": "https://www.xinpianchang.com/a13657009",
    "cover": "https://us-xpc5.xpccdn.com/1244d0ac-6d57-4884-bd67-9c58732ab98f/8c92051c-f476-4212-8e45-b4c730a0772a.jpg",
    "duration": 0,
    "categories": "摄影-其他",
    "count_view": 174,
    "count_like": 170,
    "count_collect": 0,
    "author": "栖光文化"
  },
  {
    "id": 13657008,
    "title": "Miuns Plus Multiply",
    "web_url": "https://www.xinpianchang.com/a13657008",
    "cover": "https://us-xpc5.xpccdn.com/71a9c58e-bf9d-47b6-b7a8-e61f03d0022e/c8957623-ce73-43e0-a72c-3d320c1af5ed.jpg",
    "duration": 0,
    "categories": "视觉探索-概念短片二维动画-手绘动画",
    "count_view": 2132,
    "count_like": 340,
    "count_collect": 0,
    "author": "栖光文化"
  },
  {
    "id": 13657005,
    "title": "Mate Go+",
    "web_url": "https://www.xinpianchang.com/a13657005",
    "cover": "https://us-xpc5.xpccdn.com/4b459ab8-e00d-48c1-84a4-f5e7edc534da/313288c2-ede0-4121-8086-a7d2c50f67ec.jpg",
    "duration": 0,
    "categories": "广告片-产品广告三维CG-三维动画",
    "count_view": 193,
    "count_like": 189,
    "count_collect": 0,
    "author": "栖光文化"
  },
  {
    "id": 13657004,
    "title": "Lions Series 2025 - Behind the Scenes",
    "web_url": "https://www.xinpianchang.com/a13657004",
    "cover": "https://us-xpc5.xpccdn.com/71fbc89c-8db4-4780-873c-f325ec02c911/5c4b3060-7c23-44b4-a6aa-801f1faf6725.jpg",
    "duration": 0,
    "categories": "二维动画-MG动画",
    "count_view": 174,
    "count_like": 172,
    "count_collect": 0,
    "author": "栖光文化"
  },
  {
    "id": 13657003,
    "title": "Lions Series 2025",
    "web_url": "https://www.xinpianchang.com/a13657003",
    "cover": "https://us-xpc5.xpccdn.com/940cc3db-250d-4f03-b538-aa640fb4847c/a7415544-65ab-46fe-bb40-1c7f8b92ddc2.jpg",
    "duration": 0,
    "categories": "AIGC-创意",
    "count_view": 2189,
    "count_like": 367,
    "count_collect": 0,
    "author": "栖光文化"
  },
  {
    "id": 13657002,
    "title": "KOMERČNÍ BANKA",
    "web_url": "https://www.xinpianchang.com/a13657002",
    "cover": "https://us-xpc5.xpccdn.com/8b7ddb46-e5d6-409d-bb98-00a90bd47a1f/a9ee5c28-eb14-4896-8573-56950f04616b.jpg",
    "duration": 0,
    "categories": "广告片-地产/金融",
    "count_view": 2172,
    "count_like": 356,
    "count_collect": 0,
    "author": "栖光文化"
  },
  {
    "id": 13657001,
    "title": "It's About Time Unsurance Does That",
    "web_url": "https://www.xinpianchang.com/a13657001",
    "cover": "https://us-xpc5.xpccdn.com/ec653f45-7e17-4666-9552-694d46080cf4/7b607000-a807-44e1-9438-150234be3e36.jpg",
    "duration": 0,
    "categories": "广告片-TVC广告",
    "count_view": 198,
    "count_like": 199,
    "count_collect": 0,
    "author": "栖光文化"
  },
  {
    "id": 13656999,
    "title": "In Transition",
    "web_url": "https://www.xinpianchang.com/a13656999",
    "cover": "https://us-xpc5.xpccdn.com/f7f1094f-e9f1-4e91-9fd4-388b30721ce3/14b72f62-5a1e-44fb-a319-4dae0db321bf.jpg",
    "duration": 0,
    "categories": "视觉探索-视觉艺术",
    "count_view": 178,
    "count_like": 176,
    "count_collect": 0,
    "author": "栖光文化"
  },
  {
    "id": 13656998,
    "title": "I Think Of You Dying",
    "web_url": "https://www.xinpianchang.com/a13656998",
    "cover": "https://us-xpc5.xpccdn.com/2a5f0918-6170-4fa1-8059-c4e4606f6560/c3898be1-2473-4cf4-9d53-32f9b322aed1.jpg",
    "duration": 0,
    "categories": "广告片-TVC广告广告片-剧情广告",
    "count_view": 2115,
    "count_like": 324,
    "count_collect": 0,
    "author": "栖光文化"
  },
  {
    "id": 13656997,
    "title": "Hyperboot Launch",
    "web_url": "https://www.xinpianchang.com/a13656997",
    "cover": "https://us-xpc5.xpccdn.com/b4bc5c00-ec00-47aa-8820-4a66b352b21c/c712dcb1-3d7e-4a71-9a83-23092a4bb5f8.jpg",
    "duration": 0,
    "categories": "广告片-服装/时尚三维CG-三维动画",
    "count_view": 2258,
    "count_like": 367,
    "count_collect": 0,
    "author": "栖光文化"
  },
  {
    "id": 13656996,
    "title": "Huawei Mate Xt Ultimate Design Brand Fil",
    "web_url": "https://www.xinpianchang.com/a13656996",
    "cover": "https://us-xpc5.xpccdn.com/a4e965c3-e565-4b0f-9012-493899e5bcff/4ccd1592-6141-4641-a4a9-91434a78c88b.jpg",
    "duration": 0,
    "categories": "广告片-产品广告广告片-手机/数码",
    "count_view": 197,
    "count_like": 199,
    "count_collect": 0,
    "author": "栖光文化"
  },
  {
    "id": 13656995,
    "title": "Huawei Mate Xt Ultimate Design",
    "web_url": "https://www.xinpianchang.com/a13656995",
    "cover": "https://us-xpc5.xpccdn.com/002204a2-4f5a-438f-8325-f753cf0dbda2/7810d167-f532-4809-8182-b35ac129e536.jpg",
    "duration": 0,
    "categories": "三维CG-CG/特效广告片-手机/数码",
    "count_view": 209,
    "count_like": 212,
    "count_collect": 0,
    "author": "栖光文化"
  },
  {
    "id": 13656994,
    "title": "Heavyweight - Behind The Scenes",
    "web_url": "https://www.xinpianchang.com/a13656994",
    "cover": "https://us-xpc5.xpccdn.com/394c80f6-8fd8-4c8c-b6c3-4f025052e636/9ce30109-707d-40e0-b49e-d1aa56b80a54.jpg",
    "duration": 0,
    "categories": "其他-其他",
    "count_view": 11,
    "count_like": 9,
    "count_collect": 0,
    "author": "栖光文化"
  },
  {
    "id": 13656993,
    "title": "Heavyweight",
    "web_url": "https://www.xinpianchang.com/a13656993",
    "cover": "https://us-xpc5.xpccdn.com/d2cf4fab-6b04-41f7-8b4b-8185e28db0eb/45951237-4c73-40d6-b5d2-d77f958cd8e0.jpg",
    "duration": 0,
    "categories": "时尚-品牌视觉",
    "count_view": 171,
    "count_like": 168,
    "count_collect": 0,
    "author": "栖光文化"
  },
  {
    "id": 13656988,
    "title": "Heart Of Joy Octowaltz",
    "web_url": "https://www.xinpianchang.com/a13656988",
    "cover": "https://us-xpc5.xpccdn.com/dea3d603-51f3-4c45-8086-d002caa8f058/91b061c3-2bac-4402-92bb-b43b83f5fdd5.jpg",
    "duration": 0,
    "categories": "广告片-汽车",
    "count_view": 2214,
    "count_like": 344,
    "count_collect": 0,
    "author": "栖光文化"
  },
  {
    "id": 13656986,
    "title": "Everything Covered",
    "web_url": "https://www.xinpianchang.com/a13656986",
    "cover": "https://us-xpc5.xpccdn.com/9c2f63ab-81b2-44d8-8d08-39748693ca20/313dd448-1fd2-42d0-8d60-c8c7864bd86d.jpg",
    "duration": 0,
    "categories": "二维动画-手绘动画",
    "count_view": 2206,
    "count_like": 348,
    "count_collect": 0,
    "author": "栖光文化"
  },
  {
    "id": 13656985,
    "title": "Echoes Of Creation",
    "web_url": "https://www.xinpianchang.com/a13656985",
    "cover": "https://us-xpc5.xpccdn.com/5d63dc22-11de-4e4c-908b-d61f3f78a113/f9534588-7001-41b1-a801-f354ff01add7.jpg",
    "duration": 0,
    "categories": "宣传片-其他",
    "count_view": 2238,
    "count_like": 386,
    "count_collect": 0,
    "author": "栖光文化"
  },
  {
    "id": 13656984,
    "title": "Aurora - Behind the Scenes",
    "web_url": "https://www.xinpianchang.com/a13656984",
    "cover": "https://us-xpc5.xpccdn.com/cd454e94-0443-4ae9-98df-a0aa4a2d0581/dacd8596-5d0f-4c27-87bf-d9b4d043c1fc.jpg",
    "duration": 0,
    "categories": "广告片-汽车三维CG-三维动画",
    "count_view": 184,
    "count_like": 185,
    "count_collect": 0,
    "author": "栖光文化"
  },
  {
    "id": 13656982,
    "title": "Aurora",
    "web_url": "https://www.xinpianchang.com/a13656982",
    "cover": "https://us-xpc5.xpccdn.com/a527de1f-e740-4d20-ba38-ad5966cc4a37/41613e0d-e0b3-4f66-a9f6-269dd4791fa8.jpg",
    "duration": 0,
    "categories": "广告片-汽车",
    "count_view": 2245,
    "count_like": 369,
    "count_collect": 0,
    "author": "栖光文化"
  },
  {
    "id": 13656981,
    "title": "Atlas Festival 2025 Titles - Behind the",
    "web_url": "https://www.xinpianchang.com/a13656981",
    "cover": "https://us-xpc5.xpccdn.com/d8f4ad18-aeff-47f5-8da6-fce1d4cc3e9d/8bdccbc1-cce9-4b8d-8fb0-4755851c8987.jpg",
    "duration": 0,
    "categories": "其他-其他",
    "count_view": 17,
    "count_like": 15,
    "count_collect": 0,
    "author": "栖光文化"
  },
  {
    "id": 13656980,
    "title": "Atlas Festival 2025 Titles",
    "web_url": "https://www.xinpianchang.com/a13656980",
    "cover": "https://us-xpc5.xpccdn.com/10029caa-5cf6-4a3d-8fbc-1ded4a4cae7c/8d8cb6ee-9111-49f0-b488-3c1a30473ffb.jpg",
    "duration": 0,
    "categories": "广告片-TVC广告",
    "count_view": 179,
    "count_like": 177,
    "count_collect": 0,
    "author": "栖光文化"
  },
  {
    "id": 13656979,
    "title": "Asura",
    "web_url": "https://www.xinpianchang.com/a13656979",
    "cover": "https://us-xpc5.xpccdn.com/81e3bfa3-850f-4bd1-b281-1f66ed806db1/0e039192-fd37-4968-9774-9eda8d29ae1d.jpg",
    "duration": 0,
    "categories": "广告片-游戏/娱乐",
    "count_view": 2280,
    "count_like": 370,
    "count_collect": 0,
    "author": "栖光文化"
  },
  {
    "id": 13656978,
    "title": "App O‘Clock",
    "web_url": "https://www.xinpianchang.com/a13656978",
    "cover": "https://us-xpc5.xpccdn.com/10d7db0b-99ab-46de-ad24-7517729c244b/c4bf8ab3-4afd-4b8f-a04c-b566a02d996c.jpg",
    "duration": 0,
    "categories": "广告片-互联网服务三维CG-三维动画",
    "count_view": 181,
    "count_like": 182,
    "count_collect": 0,
    "author": "栖光文化"
  },
  {
    "id": 13656977,
    "title": "Anno 117 - Pax Pomana Trailer",
    "web_url": "https://www.xinpianchang.com/a13656977",
    "cover": "https://us-xpc5.xpccdn.com/6ac71219-7264-4994-a5fb-9db3a869ba84/b517bccb-2629-4ae7-b533-70cf25a915ee.jpg",
    "duration": 0,
    "categories": "广告片-TVC广告",
    "count_view": 2258,
    "count_like": 372,
    "count_collect": 0,
    "author": "栖光文化"
  },
  {
    "id": 13656974,
    "title": "70 Ans - Behind The Scenes",
    "web_url": "https://www.xinpianchang.com/a13656974",
    "cover": "https://us-xpc5.xpccdn.com/570a39f1-99e1-40cd-9e4d-a8b2daa36a6f/9cf72815-46f8-4b57-831f-8bb02d002f53.jpg",
    "duration": 0,
    "categories": "广告片-TVC广告广告片-汽车",
    "count_view": 2191,
    "count_like": 356,
    "count_collect": 0,
    "author": "栖光文化"
  },
  {
    "id": 13656973,
    "title": "70 Ans",
    "web_url": "https://www.xinpianchang.com/a13656973",
    "cover": "https://us-xpc5.xpccdn.com/d8451f5a-0284-4794-b4a8-346bc9a8251a/03273e8b-a8c0-413a-be03-bef7a3767ffd.jpg",
    "duration": 0,
    "categories": "广告片-汽车",
    "count_view": 2266,
    "count_like": 371,
    "count_collect": 0,
    "author": "栖光文化"
  }
]